dbaas_networkapi/__init__.py
dbaas_networkapi/dbaas_api.py
dbaas_networkapi/equipments.py
dbaas_networkapi/models.py
dbaas_networkapi/provider.py
dbaas_networkapi-0.1.0.dist-info/DESCRIPTION.rst
dbaas_networkapi-0.1.0.dist-info/METADATA
dbaas_networkapi-0.1.0.dist-info/RECORD
dbaas_networkapi-0.1.0.dist-info/WHEEL
dbaas_networkapi-0.1.0.dist-info/metadata.json
dbaas_networkapi-0.1.0.dist-info/top_level.txt
