Metadata-Version: 2.0
Name: dbaas-networkapi
Version: 0.1.0
Summary: DBaaS NetworkApi is a simple network api wrapper for DBaaS
Home-page: https://github.com/tayanemoura/dbaas_networkapi
Author: Tayane Silva Fernandes de Moura
Author-email: tayanemoura@id.uff.br
License: MIT license
Keywords: dbaas_networkapi
Platform: UNKNOWN
Classifier: Development Status :: 2 - Pre-Alpha
Classifier: Intended Audience :: Developers
Classifier: License :: OSI Approved :: MIT License
Classifier: Natural Language :: English
Classifier: Programming Language :: Python :: 2
Classifier: Programming Language :: Python :: 2.6
Classifier: Programming Language :: Python :: 2.7
Classifier: Programming Language :: Python :: 3
Classifier: Programming Language :: Python :: 3.3
Classifier: Programming Language :: Python :: 3.4
Classifier: Programming Language :: Python :: 3.5
